querychart_package/.schemawiz_config3
querychart_package/__init__.py
querychart_package/data.csv
querychart_package/fieldcounts.tsv
querychart_package/gant_data.csv
querychart_package/ganter.py
querychart_package/local_sqlite_db
querychart_package/plan.xlsx
querychart_package/querychart.py
querychart_package/sales.csv
querychart_package/sampledata.csv
querychart_package/widesales.csv
querychart_package-2.0.6.dist-info/METADATA
querychart_package-2.0.6.dist-info/WHEEL
querychart_package-2.0.6.dist-info/RECORD
